teleencrypt/__init__.py
teleencrypt/teleencrypt.py
teleencrypt/const/__init__.py
teleencrypt/const/click_setting.cpython-36m-aarch64-linux-gnu.so
teleencrypt/const/setup_content.cpython-36m-aarch64-linux-gnu.so
teleencrypt/utils/__init__.py
teleencrypt/utils/encrypt_utils.cpython-36m-aarch64-linux-gnu.so
teleencrypt/utils/string_utils.cpython-36m-aarch64-linux-gnu.so
teleencrypt-0.1.3.dist-info/DESCRIPTION.rst
teleencrypt-0.1.3.dist-info/METADATA
teleencrypt-0.1.3.dist-info/RECORD
teleencrypt-0.1.3.dist-info/WHEEL
teleencrypt-0.1.3.dist-info/entry_points.txt
teleencrypt-0.1.3.dist-info/metadata.json
teleencrypt-0.1.3.dist-info/top_level.txt
