Metadata-Version: 2.0
Name: teleencrypt
Version: 0.1.3
Summary: Command line toolkit for tele encrypt
Home-page: UNKNOWN
Author: imason
Author-email: moy7@chinatelecom.cn
License: UNKNOWN
Keywords: teleencrypt
Platform: UNKNOWN
Classifier: Programming Language :: Python :: 3
Classifier: License :: OSI Approved :: MIT License
Classifier: Operating System :: OS Independent
Requires-Python: >=3.6,
Requires-Dist: Click (>=8.0.4)
Requires-Dist: Cython (==0.29.4)
Requires-Dist: PyYAML (==6.0)
